AUTHORS.rst
CONTRIBUTING.rst
HISTORY.rst
LICENSE
MANIFEST.in
README.md
setup.cfg
setup.py
gitenberg/__init__.py
gitenberg/__init__.pyc
gitenberg.metadata.egg-info/PKG-INFO
gitenberg.metadata.egg-info/SOURCES.txt
gitenberg.metadata.egg-info/dependency_links.txt
gitenberg.metadata.egg-info/namespace_packages.txt
gitenberg.metadata.egg-info/not-zip-safe
gitenberg.metadata.egg-info/requires.txt
gitenberg.metadata.egg-info/top_level.txt
gitenberg/metadata/__init__.py
gitenberg/metadata/__init__.pyc
gitenberg/metadata/licenses.py
gitenberg/metadata/licenses.pyc
gitenberg/metadata/marc.py
gitenberg/metadata/marc.pyc
gitenberg/metadata/pandata.py
gitenberg/metadata/pandata.pyc
gitenberg/metadata/parameters.py
gitenberg/metadata/parameters.pyc
gitenberg/metadata/pg_rdf.py
gitenberg/metadata/pg_rdf.pyc
tests/__init__.py
tests/__init__.pyc
tests/test.py
tests/test.pyc