Metadata-Version: 1.1
Name: gitenberg.metadata
Version: 0.1.7
Summary: metadata development - formats and machinery for GITenberg
Home-page: https://github.com/gitenberg-dev/metadata
Author: Eric Hellman
Author-email: eric@hellman.net
License: GPL
Keywords: books ebooks gitenberg gutenberg epub metadata
Platform: UNKNOWN
Classifier: Development Status :: 3 - Alpha
Classifier: Intended Audience :: Developers
Classifier: Intended Audience :: Education
Classifier: License :: OSI Approved :: GNU Lesser General Public License v3 or later (LGPLv3+)
Classifier: Natural Language :: English
Classifier: Programming Language :: Python :: 2
Classifier: Programming Language :: Python :: 2.7
